hyfive/__init__.hy
hyfive/__init__.py
hyfive/column.hy
hyfive/curried.hy
hyfive/dataframe.hy
hyfive/utils.hy
hyfive-0.1.7.dist-info/LICENSE.txt
hyfive-0.1.7.dist-info/METADATA
hyfive-0.1.7.dist-info/WHEEL
hyfive-0.1.7.dist-info/top_level.txt
hyfive-0.1.7.dist-info/RECORD
