Metadata-Version: 2.1
Name: hyfive
Version: 0.1.7
Summary: A Hy library that provides a Lispy functional                 interface by wrapping Python's popular data libraries,                 such as Pandas and Matplotlib.
Home-page: https://gitlab.com/arithmox/hyfive
Author: Anthony Khong
Author-email: anthony@arithmox.ai
License: gpl-3.0
Platform: UNKNOWN
Classifier: Development Status :: 4 - Beta
Classifier: Intended Audience :: Developers
Classifier: License :: OSI Approved :: GNU General Public License v3 (GPLv3)
Classifier: Programming Language :: Python :: 3
Classifier: Programming Language :: Python :: 3.5
Classifier: Programming Language :: Python :: 3.6
Classifier: Programming Language :: Python :: 3.7
Classifier: Programming Language :: Python :: 3.8
Classifier: Operating System :: OS Independent
Classifier: Topic :: Database
Requires-Dist: cytoolz (>=0.10.0)
Requires-Dist: dask-ml (>=1.0.0)
Requires-Dist: dask (>=2.3.0)
Requires-Dist: hy (>=0.17.0)
Requires-Dist: hypothesis (>=4.32.3)
Requires-Dist: ipython (>=7.7.0)
Requires-Dist: matplotlib (>=3.1.1)
Requires-Dist: pandas (>=0.25.0)
Requires-Dist: pdbpp (>=0.10.0)
Requires-Dist: pytest-cov (>=2.7.1)
Requires-Dist: pytest (>=5.0.1)
Requires-Dist: scikit-learn (>=0.21.3)
Requires-Dist: scipy (>=1.3.1)
